nonebot_plugin_cocdicer/__init__.py
nonebot_plugin_cocdicer/cards.py
nonebot_plugin_cocdicer/dices.py
nonebot_plugin_cocdicer/investigator.py
nonebot_plugin_cocdicer/madness.py
nonebot_plugin_cocdicer/messages.py
nonebot_plugin_cocdicer/san_check.py
nonebot_plugin_cocdicer/util.py
nonebot_plugin_cocdicer-0.4.0.dist-info/LICENSE
nonebot_plugin_cocdicer-0.4.0.dist-info/WHEEL
nonebot_plugin_cocdicer-0.4.0.dist-info/METADATA
nonebot_plugin_cocdicer-0.4.0.dist-info/RECORD
