Metadata-Version: 2.1
Name: nonebot-plugin-cocdicer
Version: 0.4.0
Summary: A COC dice plugin for Nonebot2
Home-page: https://github.com/abrahum/nonebot_plugin_cocdicer
License: GPLv3
Keywords: nonebot,nonebot2,coc,dice
Author: abrahumlink
Author-email: 307887491@qq.com
Requires-Python: >=3.7.3,<4.0.0
Classifier: License :: Other/Proprietary License
Classifier: Programming Language :: Python :: 3
Classifier: Programming Language :: Python :: 3.10
Classifier: Programming Language :: Python :: 3.8
Classifier: Programming Language :: Python :: 3.9
Requires-Dist: diro-py (>=0.1,<0.2)
Requires-Dist: nonebot-adapter-onebot (>=2.0.0-beta.1,<3.0.0)
Requires-Dist: nonebot2 (>=2.0.0-beta.1,<3.0.0)
Requires-Dist: ujson (>=4.0.0)
Project-URL: Documentation, https://github.com/abrahum/nonebot_plugin_cocdicer#readme
Project-URL: Repository, https://github.com/abrahum/nonebot_plugin_cocdicer
